{
    "blockchainData": {
        "currentDifficulty": 2,
        "verified": true,
        "blocks": [
            {
                "index": 0,
                "data": {},
                "hash": "0",
                "previousHash": null,
                "timestamp": "2022-03-14T22:04:25.746Z",
                "pow": 0,
                "difficulty": 3
            },
            {
                "index": 1,
                "data": {
                    "from": "1180745f-f671-4181-ab76-2178ece4fad6",
                    "to": "7af83270-8441-4803-a12f-9aeead33aa73",
                    "amount": 7
                },
                "hash": "0004fcf82d5a492d2bea8f0c79d13c7588e5e809a9d176270931e9a23ef91db1",
                "previousHash": "0",
                "timestamp": "2022-03-14T22:04:25.746Z",
                "pow": 1860,
                "difficulty": 3
            },
            {
                "index": 2,
                "data": {
                    "from": "b3fb7be7-de7f-4403-95e9-5b06c2ec5357",
                    "to": "b02bb20b-1f40-4773-95c6-e328ebbd357f",
                    "amount": 100
                },
                "hash": "000068088c3c5d3b5929a7a25d5c5b880d7ee65d38e7069dd6769157dd1327ad",
                "previousHash": "0004fcf82d5a492d2bea8f0c79d13c7588e5e809a9d176270931e9a23ef91db1",
                "timestamp": "2022-03-14T22:04:25.758Z",
                "pow": 30246,
                "difficulty": 4
            },
            {
                "index": 3,
                "data": {
                    "from": "c3bb1e49-4472-413d-aef3-2d5dccc3545f",
                    "to": "36a7b9fc-088e-4f12-bdf3-e3855b119e19",
                    "amount": 50
                },
                "hash": "000e638bbb20000c4e5fc5a7594315191d05814d6459fa46dadc392466b0f051",
                "previousHash": "000068088c3c5d3b5929a7a25d5c5b880d7ee65d38e7069dd6769157dd1327ad",
                "timestamp": "2022-03-14T22:04:25.866Z",
                "pow": 6960,
                "difficulty": 3
            }
        ]
    }
}